{"type":"FeatureCollection","features":[{"type":"Feature","geometry":{"type":"Point","coordinates":[1.525737047195427,42.50582373522425]},"properties":{"localrank":1,"maki":"park","name":"Parc Central","name_de":"Parc Central","name_en":"Parc Central","name_es":"Parc Central","name_fr":"Parc Central","osm_id":1000006275507,"ref":"","scalerank":3,"type":"Park"}}],"name":"poi_label"}